edges_io/__init__.py
edges_io/_structure.py
edges_io/auxiliary.py
edges_io/cli.py
edges_io/config.py
edges_io/io.py
edges_io/io3.py
edges_io/logging.py
edges_io/types.py
edges_io/utils.py
edges_io/vna.py
edges_io/data/__init__.py
edges_io/data/antenna_simulators.toml
edges_io/data/calibration_loads.toml
edges_io/test_data/__init__.py
edges_io/test_data/example.s2p
edges_io/test_data/observation.yaml
edges_io/test_data/old_resistance_file.csv
edges_io/test_data/s11_db.s1p
edges_io/test_data/sample.acq
edges_io/test_data/thermlog_test_data.txt
edges_io/test_data/weather_test_data.txt
edges_io/test_data/Receiver01_25C_2019_11_26_040_to_200MHz/Notes.txt
edges_io/test_data/Receiver01_25C_2019_11_26_040_to_200MHz/Resistance/Ambient_01_2019_329_16_02_35_lab.csv
edges_io/test_data/Receiver01_25C_2019_11_26_040_to_200MHz/Resistance/AntSim2_01_2019_336_14_53_19_lab.csv
edges_io/test_data/Receiver01_25C_2019_11_26_040_to_200MHz/Resistance/AntSim3_01_2019_337_16_30_31_lab.csv
edges_io/test_data/Receiver01_25C_2019_11_26_040_to_200MHz/Resistance/AntSim4_01_2019_338_16_55_22_lab.csv
edges_io/test_data/Receiver01_25C_2019_11_26_040_to_200MHz/Resistance/HotLoad_01_2019_330_16_38_16_lab.csv
edges_io/test_data/Receiver01_25C_2019_11_26_040_to_200MHz/Resistance/LongCableOpen_01_2019_334_11_43_15_lab.csv
edges_io/test_data/Receiver01_25C_2019_11_26_040_to_200MHz/Resistance/LongCableShorted_01_2019_333_13_17_29_lab.csv
edges_io/test_data/Receiver01_25C_2019_11_26_040_to_200MHz/S11/Ambient01/External01.s1p
edges_io/test_data/Receiver01_25C_2019_11_26_040_to_200MHz/S11/Ambient01/External02.s1p
edges_io/test_data/Receiver01_25C_2019_11_26_040_to_200MHz/S11/Ambient01/Match01.s1p
edges_io/test_data/Receiver01_25C_2019_11_26_040_to_200MHz/S11/Ambient01/Match02.s1p
edges_io/test_data/Receiver01_25C_2019_11_26_040_to_200MHz/S11/Ambient01/Open01.s1p
edges_io/test_data/Receiver01_25C_2019_11_26_040_to_200MHz/S11/Ambient01/Open02.s1p
edges_io-4.1.8.dist-info/AUTHORS.rst
edges_io-4.1.8.dist-info/LICENSE.txt
edges_io-4.1.8.dist-info/METADATA
edges_io-4.1.8.dist-info/WHEEL
edges_io-4.1.8.dist-info/entry_points.txt
edges_io-4.1.8.dist-info/top_level.txt
edges_io-4.1.8.dist-info/RECORD
