Metadata-Version: 2.1
Name: edges-io
Version: 4.1.8
Summary: Module for reading EDGES data and working with EDGES databases.
Home-page: https://github.com/edges-collab/edges-io
Author: EDGES Collaboration
Author-email: steven.g.murray@asu.edu
License: mit
Platform: any
Classifier: Development Status :: 4 - Beta
Classifier: Programming Language :: Python
License-File: LICENSE.txt
License-File: AUTHORS.rst
Requires-Dist: numpy >=2.0
Requires-Dist: scipy
Requires-Dist: h5py
Requires-Dist: read-acq >=1.0.0
Requires-Dist: cached-property
Requires-Dist: bidict
Requires-Dist: pyyaml
Requires-Dist: rich
Requires-Dist: attrs
Requires-Dist: toml
Requires-Dist: dill
Requires-Dist: psutil
Requires-Dist: hickle >=5.0.0.dev0
Requires-Dist: astropy >=5.0
Requires-Dist: hickleable >=0.2.4
Requires-Dist: frozendict
Requires-Dist: importlib-metadata ; python_version < "3.8"
Provides-Extra: dev
Requires-Dist: pre-commit ; extra == 'dev'
Requires-Dist: pytest <8.0 ; extra == 'dev'
Requires-Dist: edges-io[docs] ; extra == 'dev'
Provides-Extra: docs
Requires-Dist: ipython ; extra == 'docs'
Requires-Dist: nbsphinx ; extra == 'docs'
Requires-Dist: numpydoc ; extra == 'docs'
Requires-Dist: sphinx >=4.0 ; extra == 'docs'
Requires-Dist: sphinx-click ; extra == 'docs'
Requires-Dist: furo ; extra == 'docs'
